{
  "story_id": "2026-05-08-pentagon-releases-swath-of-378036a0ec",
  "headline_seed": "Pentagon releases swath of UFO files - Politico",
  "post_type": "REPORT",
  "confidence": 0.88,
  "published_at": "2026-05-08T17:59:51.867084+00:00",
  "draft_text": "The Pentagon released 162 UFO files Friday at war.gov/UFO, spanning the 1940s to present. NBC News and CNN both confirm the documents include no evidence of extraterrestrial contact. The government drew no conclusions \u2014 Trump told Americans to decide for themselves."
}